<annotation>
	<folder></folder>
	<filename>frame0190_jpg.rf.aa6f21eb9d9967f4cb6a8ad7a3601d41.jpg</filename>
	<path>frame0190_jpg.rf.aa6f21eb9d9967f4cb6a8ad7a3601d41.jpg</path>
	<source>
		<database>roboflow.ai</database>
	</source>
	<size>
		<width>416</width>
		<height>416</height>
		<depth>3</depth>
	</size>
	<segmented>0</segmented>
	<object>
		<name>Roblox-Avatar</name>
		<pose>Unspecified</pose>
		<truncated>0</truncated>
		<difficult>0</difficult>
		<occluded>0</occluded>
		<bndbox>
			<xmin>47</xmin>
			<xmax>94</xmax>
			<ymin>1</ymin>
			<ymax>77</ymax>
		</bndbox>
	</object>
	<object>
		<name>Roblox-Avatar</name>
		<pose>Unspecified</pose>
		<truncated>0</truncated>
		<difficult>0</difficult>
		<occluded>0</occluded>
		<bndbox>
			<xmin>195</xmin>
			<xmax>266</xmax>
			<ymin>1</ymin>
			<ymax>166</ymax>
		</bndbox>
	</object>
	<object>
		<name>Roblox-Avatar</name>
		<pose>Unspecified</pose>
		<truncated>0</truncated>
		<difficult>0</difficult>
		<occluded>0</occluded>
		<bndbox>
			<xmin>103</xmin>
			<xmax>115</xmax>
			<ymin>167</ymin>
			<ymax>179</ymax>
		</bndbox>
	</object>
	<object>
		<name>Roblox-Avatar</name>
		<pose>Unspecified</pose>
		<truncated>0</truncated>
		<difficult>0</difficult>
		<occluded>0</occluded>
		<bndbox>
			<xmin>148</xmin>
			<xmax>168</xmax>
			<ymin>167</ymin>
			<ymax>223</ymax>
		</bndbox>
	</object>
	<object>
		<name>Roblox-Avatar</name>
		<pose>Unspecified</pose>
		<truncated>0</truncated>
		<difficult>0</difficult>
		<occluded>0</occluded>
		<bndbox>
			<xmin>70</xmin>
			<xmax>124</xmax>
			<ymin>167</ymin>
			<ymax>306</ymax>
		</bndbox>
	</object>
	<object>
		<name>Roblox-Avatar</name>
		<pose>Unspecified</pose>
		<truncated>0</truncated>
		<difficult>0</difficult>
		<occluded>0</occluded>
		<bndbox>
			<xmin>143</xmin>
			<xmax>187</xmax>
			<ymin>177</ymin>
			<ymax>367</ymax>
		</bndbox>
	</object>
	<object>
		<name>Roblox-Avatar</name>
		<pose>Unspecified</pose>
		<truncated>0</truncated>
		<difficult>0</difficult>
		<occluded>0</occluded>
		<bndbox>
			<xmin>276</xmin>
			<xmax>331</xmax>
			<ymin>197</ymin>
			<ymax>340</ymax>
		</bndbox>
	</object>
</annotation>
