<annotation>
	<folder></folder>
	<filename>frame0479_jpg.rf.3ed12d639a7c88f0cab6bb1526666233.jpg</filename>
	<path>frame0479_jpg.rf.3ed12d639a7c88f0cab6bb1526666233.jpg</path>
	<source>
		<database>roboflow.ai</database>
	</source>
	<size>
		<width>416</width>
		<height>416</height>
		<depth>3</depth>
	</size>
	<segmented>0</segmented>
	<object>
		<name>Roblox-Avatar</name>
		<pose>Unspecified</pose>
		<truncated>0</truncated>
		<difficult>0</difficult>
		<occluded>0</occluded>
		<bndbox>
			<xmin>206</xmin>
			<xmax>311</xmax>
			<ymin>85</ymin>
			<ymax>344</ymax>
		</bndbox>
	</object>
</annotation>
