<annotation>
	<folder></folder>
	<filename>frame0230_jpg.rf.915e5423dc9f89e1b6f627957803dc70.jpg</filename>
	<path>frame0230_jpg.rf.915e5423dc9f89e1b6f627957803dc70.jpg</path>
	<source>
		<database>roboflow.ai</database>
	</source>
	<size>
		<width>416</width>
		<height>416</height>
		<depth>3</depth>
	</size>
	<segmented>0</segmented>
	<object>
		<name>Roblox-Avatar</name>
		<pose>Unspecified</pose>
		<truncated>0</truncated>
		<difficult>0</difficult>
		<occluded>0</occluded>
		<bndbox>
			<xmin>338</xmin>
			<xmax>411</xmax>
			<ymin>117</ymin>
			<ymax>174</ymax>
		</bndbox>
	</object>
	<object>
		<name>Roblox-Avatar</name>
		<pose>Unspecified</pose>
		<truncated>0</truncated>
		<difficult>0</difficult>
		<occluded>0</occluded>
		<bndbox>
			<xmin>51</xmin>
			<xmax>99</xmax>
			<ymin>285</ymin>
			<ymax>416</ymax>
		</bndbox>
	</object>
	<object>
		<name>Roblox-Avatar</name>
		<pose>Unspecified</pose>
		<truncated>0</truncated>
		<difficult>0</difficult>
		<occluded>0</occluded>
		<bndbox>
			<xmin>102</xmin>
			<xmax>174</xmax>
			<ymin>313</ymin>
			<ymax>416</ymax>
		</bndbox>
	</object>
	<object>
		<name>Roblox-Avatar</name>
		<pose>Unspecified</pose>
		<truncated>0</truncated>
		<difficult>0</difficult>
		<occluded>0</occluded>
		<bndbox>
			<xmin>273</xmin>
			<xmax>416</xmax>
			<ymin>181</ymin>
			<ymax>416</ymax>
		</bndbox>
	</object>
</annotation>
